prophet_numpyro/__init__.py
prophet_numpyro/base.py
prophet_numpyro/exogenous_priors.py
prophet_numpyro/hierarchical_prophet/__init__.py
prophet_numpyro/hierarchical_prophet/_distribution.py
prophet_numpyro/hierarchical_prophet/_transformations.py
prophet_numpyro/hierarchical_prophet/_utils.py
prophet_numpyro/hierarchical_prophet/prophet.py
prophet_numpyro/prophet/__init__.py
prophet_numpyro/prophet/jax_functions.py
prophet_numpyro/prophet/prophet.py
prophet_numpyro-0.1.0.post1.dist-info/LICENSE
prophet_numpyro-0.1.0.post1.dist-info/METADATA
prophet_numpyro-0.1.0.post1.dist-info/WHEEL
prophet_numpyro-0.1.0.post1.dist-info/RECORD
